fido2/__init__.py
fido2/attestation/__init__.py
fido2/attestation/android.py
fido2/attestation/apple.py
fido2/attestation/base.py
fido2/attestation/packed.py
fido2/attestation/tpm.py
fido2/attestation/u2f.py
fido2/cbor.py
fido2/client/__init__.py
fido2/client/win_api.py
fido2/client/windows.py
fido2/cose.py
fido2/ctap.py
fido2/ctap1.py
fido2/ctap2/__init__.py
fido2/ctap2/base.py
fido2/ctap2/bio.py
fido2/ctap2/blob.py
fido2/ctap2/config.py
fido2/ctap2/credman.py
fido2/ctap2/extensions.py
fido2/ctap2/pin.py
fido2/features.py
fido2/hid/__init__.py
fido2/hid/base.py
fido2/hid/freebsd.py
fido2/hid/linux.py
fido2/hid/macos.py
fido2/hid/netbsd.py
fido2/hid/openbsd.py
fido2/hid/windows.py
fido2/mds3.py
fido2/payment.py
fido2/pcsc.py
fido2/public_suffix_list.dat
fido2/py.typed
fido2/rpid.py
fido2/server.py
fido2/utils.py
fido2/webauthn.py
fido2-2.1.0.dist-info/METADATA
fido2-2.1.0.dist-info/WHEEL
fido2-2.1.0.dist-info/licenses/COPYING
fido2-2.1.0.dist-info/licenses/COPYING.APLv2
fido2-2.1.0.dist-info/licenses/COPYING.MPLv2
fido2-2.1.0.dist-info/RECORD
