Metadata-Version: 2.4
Name: fido2
Version: 2.1.0
Summary: FIDO2/WebAuthn library for implementing clients and servers.
License: Copyright (c) 2018 Yubico AB
License-File: COPYING
License-File: COPYING.APLv2
License-File: COPYING.MPLv2
Keywords: fido2,webauthn,ctap,u2f
Author: Dain Nilsson
Author-email: <dain@yubico.com>
Requires-Python: >=3.10, <4
Classifier: License :: OSI Approved :: BSD License
Classifier: License :: OSI Approved :: Apache Software License
Classifier: License :: OSI Approved :: Mozilla Public License 2.0 (MPL 2.0)
Classifier: Operating System :: MacOS
Classifier: Operating System :: Microsoft :: Windows
Classifier: Operating System :: POSIX :: Linux
Classifier: Development Status :: 5 - Production/Stable
Classifier: Intended Audience :: Developers
Classifier: Intended Audience :: System Administrators
Classifier: Topic :: Internet
Classifier: Topic :: Security :: Cryptography
Classifier: Topic :: Software Development :: Libraries :: Python Modules
Provides-Extra: pcsc
Requires-Dist: cryptography (>=2.6,!=35,<49)
Requires-Dist: pyscard (>=1.9,<3) ; extra == "pcsc"
Project-URL: Homepage, https://github.com/Yubico/python-fido2
